README.md
setup.cfg
setup.py
mypassword/__init__.py
mypassword/password.py
mypassword/passworify.py
mypassword.egg-info/PKG-INFO
mypassword.egg-info/SOURCES.txt
mypassword.egg-info/dependency_links.txt
mypassword.egg-info/top_level.txt