Metadata-Version: 2.1
Name: mypassword
Version: 0.1.2
Summary: Tools for generating strong passwords
Home-page: https://github.com/vinzegtz/mypassword
Author: Vicente Gutiérrez
Author-email: vinzegtz@gmail.com
License: UNKNOWN
Download-URL: https://github.com/vinzegtz/mypassword/archive/v0.1.2-beta.tar.gz
Keywords: password,pass,password-manager
Platform: UNKNOWN
Classifier: Development Status :: 4 - Beta
Classifier: Intended Audience :: Developers
Classifier: Topic :: Security
Classifier: Topic :: Security :: Cryptography
Classifier: License :: OSI Approved :: MIT License
Classifier: Programming Language :: Python :: 3
